cli_whisperer/__init__.py
cli_whisperer/__main__.py
cli_whisperer/cli.py
cli_whisperer/main.py
cli_whisperer/core/__init__.py
cli_whisperer/core/audio_recorder.py
cli_whisperer/core/file_manager.py
cli_whisperer/core/formatter.py
cli_whisperer/core/transcriber.py
cli_whisperer/integrations/__init__.py
cli_whisperer/integrations/clipboard.py
cli_whisperer/integrations/spotify_control.py
cli_whisperer/ui/__init__.py
cli_whisperer/ui/edit_manager.py
cli_whisperer/ui/export_dialog.py
cli_whisperer/ui/rich_output.py
cli_whisperer/ui/textual_app.py
cli_whisperer/ui/themes.py
cli_whisperer/ui/ui_manager.py
cli_whisperer/utils/__init__.py
cli_whisperer/utils/config.py
cli_whisperer/utils/export_manager.py
cli_whisperer/utils/history.py
cli_whisperer/utils/logger.py
cli_whisperer-1.0.0.dist-info/METADATA
cli_whisperer-1.0.0.dist-info/WHEEL
cli_whisperer-1.0.0.dist-info/entry_points.txt
cli_whisperer-1.0.0.dist-info/RECORD
