Metadata-Version: 2.4
Name: cli-whisperer
Version: 1.0.0
Summary: Voice to Text Tool with Smart File Management and OpenAI Formatting
Author-email: VinnyVanGogh <133192356+VinnyVanGogh@users.noreply.github.com>
Requires-Python: >=3.10
Requires-Dist: numba>=0.60.0
Requires-Dist: numpy
Requires-Dist: openai
Requires-Dist: openai-whisper>=20250625
Requires-Dist: pydantic
Requires-Dist: pyperclip
Requires-Dist: python-dotenv
Requires-Dist: rich
Requires-Dist: scipy
Requires-Dist: sounddevice
Requires-Dist: textual
Requires-Dist: torch>=2.5.1
Requires-Dist: transformers>=4.46.3
